{
  "IsEncrypted": false,
  "Values": {
    "AzureWebJobsStorage": "UseDevelopmentStorage=true",
    "FUNCTIONS_WORKER_RUNTIME": "node",
    "FUNCTIONS_EXTENSION_VERSION": "~4",
    "WEBSITE_NODE_DEFAULT_VERSION": "~18",
    "AzureWebJobsFeatureFlags": "EnableWorkerIndexing",
    "APP_KIND": "workflowApp",
    "AzureFunctionsJobHost__extensionBundle__id": "Microsoft.Azure.Functions.ExtensionBundle.Workflows",
    "AzureFunctionsJobHost__extensionBundle__version": "[1.*, 2.0.0)",
    "WORKFLOWS_SUBSCRIPTION_ID": "",
    "WORKFLOWS_LOCATION_NAME": "swedencentral",
    "WORKFLOWS_RESOURCE_GROUP_NAME": ""
  }
}
